evals/__init__.py
evals/api.py
evals/client.py
evals/metric.py
evals/pipeline.py
evals/query_generator.py
llmevals-0.1.0.dist-info/METADATA
llmevals-0.1.0.dist-info/WHEEL
llmevals-0.1.0.dist-info/top_level.txt
llmevals-0.1.0.dist-info/RECORD
